piro/__init__.py
piro/custom_entry.py
piro/data.py
piro/mprester.py
piro/reactions.py
piro/route.py
piro/settings.py
piro/utils.py
piro-2023.4.24.dist-info/LICENSE
piro-2023.4.24.dist-info/METADATA
piro-2023.4.24.dist-info/WHEEL
piro-2023.4.24.dist-info/top_level.txt
piro-2023.4.24.dist-info/RECORD
